MANIFEST.in
README.rst
setup.cfg
setup.py
versioneer.py
src/gelanis/__init__.py
src/gelanis/__version__.py
src/gelanis/_auto_injector.py
src/gelanis/_config.py
src/gelanis/_version.py
src/gelanis/accumulators.py
src/gelanis/broadcast.py
src/gelanis/cache_manager.py
src/gelanis/conf.py
src/gelanis/context.py
src/gelanis/exceptions.py
src/gelanis/partition.py
src/gelanis/rdd.py
src/gelanis/samplers.py
src/gelanis/statcounter.py
src/gelanis/storagelevel.py
src/gelanis/task_context.py
src/gelanis/utils.py
src/gelanis.egg-info/PKG-INFO
src/gelanis.egg-info/SOURCES.txt
src/gelanis.egg-info/dependency_links.txt
src/gelanis.egg-info/requires.txt
src/gelanis.egg-info/top_level.txt
src/gelanis/fileio/__init__.py
src/gelanis/fileio/file.py
src/gelanis/fileio/textfile.py
src/gelanis/fileio/codec/__init__.py
src/gelanis/fileio/codec/bz2.py
src/gelanis/fileio/codec/codec.py
src/gelanis/fileio/codec/gz.py
src/gelanis/fileio/codec/lzma.py
src/gelanis/fileio/codec/sevenz.py
src/gelanis/fileio/codec/tar.py
src/gelanis/fileio/codec/zip.py
src/gelanis/fileio/fs/__init__.py
src/gelanis/fileio/fs/file_system.py
src/gelanis/fileio/fs/gs.py
src/gelanis/fileio/fs/hdfs.py
src/gelanis/fileio/fs/http.py
src/gelanis/fileio/fs/local.py
src/gelanis/fileio/fs/s3.py
src/gelanis/sql/__init__.py
src/gelanis/sql/_casts.py
src/gelanis/sql/_date_time.py
src/gelanis/sql/_json.py
src/gelanis/sql/_row.py
src/gelanis/sql/_schema_utils.py
src/gelanis/sql/_statcounter.py
src/gelanis/sql/_types.py
src/gelanis/sql/_utils.py
src/gelanis/sql/column.py
src/gelanis/sql/conf.py
src/gelanis/sql/context.py
src/gelanis/sql/dataframe.py
src/gelanis/sql/functions.py
src/gelanis/sql/group.py
src/gelanis/sql/internals.py
src/gelanis/sql/readwriter.py
src/gelanis/sql/session.py
src/gelanis/sql/types.py
src/gelanis/sql/utils.py
src/gelanis/sql/_ast/__init__.py
src/gelanis/sql/_ast/ast_to_python.py
src/gelanis/sql/_expressions/__init__.py
src/gelanis/sql/_expressions/arrays.py
src/gelanis/sql/_expressions/csvs.py
src/gelanis/sql/_expressions/dates.py
src/gelanis/sql/_expressions/explodes.py
src/gelanis/sql/_expressions/expressions.py
src/gelanis/sql/_expressions/fields.py
