Metadata-Version: 2.1
Name: gelanis
Version: 0.6.2
Summary: Pure Python implementation of the Spark RDD interface.
Home-page: https://github.com/kbc-opensource/pysparkling
Author: pysparkling contributors
License: MIT
Platform: UNKNOWN
Classifier: Development Status :: 4 - Beta
Classifier: Intended Audience :: Developers
Classifier: Natural Language :: English
Classifier: License :: OSI Approved :: MIT License
Classifier: Operating System :: OS Independent
Classifier: Programming Language :: Python
Classifier: Programming Language :: Python :: 3.6
Classifier: Programming Language :: Python :: 3.7
Classifier: Programming Language :: Python :: 3.8
Classifier: Programming Language :: Python :: 3.9
Classifier: Programming Language :: Python :: Implementation :: PyPy
Provides-Extra: hdfs
Provides-Extra: performance
Provides-Extra: streaming
Provides-Extra: dev
Provides-Extra: sql
Provides-Extra: tests
Provides-Extra: scripts
